simplesundragon/simplesundragon.py
simplesundragon-0.0.2.dist-info/METADATA
simplesundragon-0.0.2.dist-info/WHEEL
simplesundragon-0.0.2.dist-info/top_level.txt
simplesundragon-0.0.2.dist-info/RECORD
